pandoraspec/__init__.py
pandoraspec/cli.py
pandoraspec/config.py
pandoraspec/constants.py
pandoraspec/core.py
pandoraspec/init.py
pandoraspec/orchestrator.py
pandoraspec/seed.py
pandoraspec/validator.py
pandoraspec/modules/__init__.py
pandoraspec/modules/ai_judge.py
pandoraspec/modules/drift.py
pandoraspec/modules/resilience.py
pandoraspec/modules/security.py
pandoraspec/reporting/__init__.py
pandoraspec/reporting/generator.py
pandoraspec/reporting/junit.py
pandoraspec/reporting/templates.py
pandoraspec/utils/__init__.py
pandoraspec/utils/logger.py
pandoraspec/utils/parsing.py
pandoraspec/utils/plugins.py
pandoraspec/utils/url.py
pandoraspec-0.3.7.dist-info/METADATA
pandoraspec-0.3.7.dist-info/WHEEL
pandoraspec-0.3.7.dist-info/entry_points.txt
pandoraspec-0.3.7.dist-info/top_level.txt
pandoraspec-0.3.7.dist-info/RECORD
