Metadata-Version: 2.4
Name: pandoraspec
Version: 0.3.7
Summary: DORA Compliance Auditor for OpenAPI Specs
Author-email: Ulises Merlan <ulimerlan@gmail.com>
License: MIT
Requires-Python: >=3.9
Requires-Dist: schemathesis==4.9.1
Requires-Dist: typer[all]
Requires-Dist: rich
Requires-Dist: weasyprint
Requires-Dist: requests
Requires-Dist: pydantic
Requires-Dist: pyyaml
Requires-Dist: openai
Provides-Extra: dev
Requires-Dist: pytest; extra == "dev"
Requires-Dist: responses; extra == "dev"
Requires-Dist: mypy; extra == "dev"
Requires-Dist: types-requests; extra == "dev"
Requires-Dist: types-PyYAML; extra == "dev"
Requires-Dist: ruff; extra == "dev"
Requires-Dist: pytest-cov; extra == "dev"
